springlabs_cc_alexis/__init__.py
springlabs_cc_alexis/main.py
springlabs_cc_alexis/prints.py
springlabs_cc_alexis/scripts/__init__.py
springlabs_cc_alexis/scripts/springlabs_cc_alexis.py
springlabs_cc_alexis-0.1.1.dist-info/LICENSE
springlabs_cc_alexis-0.1.1.dist-info/METADATA
springlabs_cc_alexis-0.1.1.dist-info/WHEEL
springlabs_cc_alexis-0.1.1.dist-info/entry_points.txt
springlabs_cc_alexis-0.1.1.dist-info/top_level.txt
springlabs_cc_alexis-0.1.1.dist-info/RECORD
