Metadata-Version: 2.1
Name: springlabs-cc-alexis
Version: 0.1.1
Summary: Springlabs Prints
Home-page: https://springlabs.ai/
Author: Alexis Hinojosa
Author-email: alexishinojosa008@gmail.com
License: UNKNOWN
Project-URL: Source Code, https://gitlab.com/AlejandroBarcenas/springlabs-django-cli
Platform: UNKNOWN
Classifier: Programming Language :: Python :: 3
Classifier: License :: OSI Approved :: MIT License
Classifier: Operating System :: OS Independent
Requires-Python: >=3.6
Requires-Dist: click (==7.1.2)
Requires-Dist: requests (==2.24.0)
